py3dotplus/__init__.py
py3dotplus/graphviz.py
py3dotplus/parser.py
py3dotplus/version.py
pydotplus/__init__.py
pydotplus/graphviz.py
pydotplus/parser.py
pydotplus/version.py
py3dotplus-1.1.0.dist-info/LICENSE
py3dotplus-1.1.0.dist-info/METADATA
py3dotplus-1.1.0.dist-info/WHEEL
py3dotplus-1.1.0.dist-info/top_level.txt
py3dotplus-1.1.0.dist-info/RECORD
