Metadata-Version: 2.1
Name: py3dotplus
Version: 1.1.0
Summary: Python interface to Graphviz's Dot language
Home-page: http://pydotplus.readthedocs.org/
Author: PyDotPlus Developers
Author-email: carlos@jenkins.co.cr
License: UNKNOWN
Keywords: graphviz dot graphs visualization
Platform: UNKNOWN
Classifier: Development Status :: 4 - Beta
Classifier: Intended Audience :: Science/Research
Classifier: License :: OSI Approved :: MIT License
Classifier: Natural Language :: English
Classifier: Operating System :: OS Independent
Classifier: Programming Language :: Python :: 2.7
Classifier: Programming Language :: Python :: 3
Classifier: Programming Language :: Python :: 3.4
Classifier: Programming Language :: Python :: 3.8
Classifier: Topic :: Scientific/Engineering :: Visualization
Classifier: Topic :: Software Development :: Libraries :: Python Modules
License-File: LICENSE
Requires-Dist: pyparsing (>=2.0.1)
